Metadata-Version: 2.1
Name: opendbm
Version: 0.0.1b6
Summary: AiCure’s OpenDBM is a software package that allows for calculation of digital biomarkers of health and functioning from video or audio of an individual’s behavior. It integrates existing tools for measurement of behavioral characteristics such as facial activity, voice, and movement into a single package for measurement of overall behavior. OpenDBM is designed for ease of use, expanding the availability of such tools to the wider scientific community.
Home-page: https://github.com/AiCure/open_dbm
Author: The OpenDBM Development Team
Author-email: opendbm@aicure.com
License: AGPL-3.0
Project-URL: Bug Tracker, https://github.com/AiCure/open_dbm/issues
Project-URL: Documentation, https://AiCure.github.io/open_dbm
Project-URL: Source Code, https://github.com/AiCure/open_dbm
Platform: any
Classifier: Intended Audience :: Science/Research
Classifier: License :: OSI Approved :: GNU Affero General Public License v3
Classifier: Operating System :: OS Independent
Classifier: Programming Language :: Python :: 3 :: Only
Classifier: Programming Language :: Python :: 3.7
Classifier: Programming Language :: Python :: 3.8
Classifier: Programming Language :: Python :: 3.9
Classifier: Topic :: Scientific/Engineering
Requires-Python: >=3.7
License-File: LICENSE
Requires-Dist: numpy (>=1.17)
Requires-Dist: pandas (>=1.1.5)
Requires-Dist: matplotlib (==3.5.2)
Requires-Dist: praat-parselmouth
Requires-Dist: watchtower
Requires-Dist: webrtcvad
Requires-Dist: imutils
Requires-Dist: more-itertools
Requires-Dist: scipy
Requires-Dist: pyyaml (==5.4.1)
Requires-Dist: pydub
Requires-Dist: deepspeech (==0.9.3)
Requires-Dist: nltk
Requires-Dist: lexicalrichness
Requires-Dist: vaderSentiment
Requires-Dist: opencv-python (>=4.5.5)
Requires-Dist: cmake ; "Windows" not in platform_system
Requires-Dist: dlib (>=19.13.0) ; "Windows" not in platform_system
Provides-Extra: test
Requires-Dist: pytest (>=6.0) ; extra == 'test'
Requires-Dist: coverage ; extra == 'test'
Requires-Dist: pre-commit ; extra == 'test'
